common/__init__.py
common/catrf.py
common/constants.py
common/custom_hgb.py
common/custom_multi.py
common/ft.py
common/io.py
common/logic.py
common/model.py
common/pipeline.py
common/plot.py
common/query.py
common/setup.py
common/transformer.py
common/utils.py
data_science_common_core-1.8.3.dist-info/METADATA
data_science_common_core-1.8.3.dist-info/WHEEL
data_science_common_core-1.8.3.dist-info/RECORD
